LICENSE.txt
MANIFEST.in
README.rst
setup.py
jk_sql/AbstractDB.py
jk_sql/AbstractDBTable.py
jk_sql/AbstractDBTable_NEW.py
jk_sql/AbstractDBTable_OLD.py
jk_sql/AbstractDataModelContainer.py
jk_sql/AbstractSQLFactory.py
jk_sql/DBColDef.py
jk_sql/DBManager.py
jk_sql/DBTableDef.py
jk_sql/DataModelContainerFile.py
jk_sql/DataModelContainerMemory.py
jk_sql/EnumDBColType.py
jk_sql/EnumDBIndexType.py
jk_sql/NotSupportedException.py
jk_sql/SQLFactory_TestWrapper.py
jk_sql/__init__.py
jk_sql.egg-info/PKG-INFO
jk_sql.egg-info/SOURCES.txt
jk_sql.egg-info/dependency_links.txt
jk_sql.egg-info/not-zip-safe
jk_sql.egg-info/top_level.txt
jk_sql/mysql/MySQLDB.py
jk_sql/mysql/MySQLTable.py
jk_sql/mysql/SQLFactory_MySQL.py
jk_sql/mysql/__init__.py
jk_sql/sqlite/SQLFactory_SQLite.py
jk_sql/sqlite/SQLiteDB.py
jk_sql/sqlite/SQLiteTable.py
jk_sql/sqlite/__init__.py