Metadata-Version: 1.1
Name: jk-sql
Version: 0.2018.1.19
Summary: This python module provides a uniform API to create, modify, read and write data to SQL tables in a database independent way.
Home-page: https://github.com/jkpubsrc/python-module-jk-fileaccess
Author: Jürgen Knauth
Author-email: pubsrc@binary-overflow.de
License: Apache 2.0
Download-URL: https://github.com/jkpubsrc/python-module-jk-fileaccess/tarball/0.2017.10.7
Keywords: file,filesystem,ssh,sftp,cifs,smb,iterating
Platform: UNKNOWN
Classifier: Development Status :: 3 - Alpha
Classifier: Programming Language :: Python :: 3.5
Classifier: License :: OSI Approved :: Apache Software License
